mdict_mcp/__init__.py
mdict_mcp/dictionary.py
mdict_mcp/server.py
mdict_mcp-0.2.4.dist-info/METADATA
mdict_mcp-0.2.4.dist-info/WHEEL
mdict_mcp-0.2.4.dist-info/entry_points.txt
mdict_mcp-0.2.4.dist-info/licenses/LICENSE
mdict_mcp-0.2.4.dist-info/RECORD
